{"swagger":"2.0","info":{"description":"API to create, update and manage transfer agent distribution commission information","version":"v1.0.0","title":"Transfer agent distribution commission information"},"host":"localhost:8080","basePath":"/IRISgi/multifonds/api/v1.0.0","schemes":["http"],"paths":{"/party/{parentEntityType}/{parentInternalId}/commdistributions":{"post":{"summary":"Creates Transfer agent distribution commission for the specified parent","description":"Creates Transfer agent distribution commission for the specified parent","operationId":"postcommdistributionsByParent","produces":["application/json"],"parameters":[{"name":"referenceId","in":"header","description":"uniqueId for security purpose","required":false,"type":"string"},{"name":"token","in":"header","description":"unique token","required":false,"type":"string"},{"name":"username","in":"header","description":"username","required":false,"type":"string"},{"name":"company","in":"header","description":"company name","required":false,"type":"string"},{"name":"command","in":"header","description":"API operations like INVOKE, VALIDATE, PROCESS can be set or by default PROCESS is set","required":false,"type":"string"},{"in":"body","name":"Payload","description":"postcommdistributionsByParent Payload","required":true,"schema":{"$ref":"#/definitions/sDistributionV1.0.0Payload"}}],"responses":{"201":{"description":"postcommdistributionsByParent Success Response","schema":{"$ref":"#/definitions/postcommdistributionsByParentSuccessResponse"}},"400":{"description":"postcommdistributionsByParent Error Response","schema":{"$ref":"#/definitions/postcommdistributionsByParentErrorResponse"}},"401":{"description":"postcommdistributionsByParent Error Response","schema":{"$ref":"#/definitions/postcommdistributionsByParentErrorResponse"}},"403":{"description":"postcommdistributionsByParent Error Response","schema":{"$ref":"#/definitions/postcommdistributionsByParentErrorResponse"}},"404":{"description":"postcommdistributionsByParent Error Response","schema":{"$ref":"#/definitions/postcommdistributionsByParentErrorResponse"}},"405":{"description":"postcommdistributionsByParent Error Response","schema":{"$ref":"#/definitions/postcommdistributionsByParentErrorResponse"}},"409":{"description":"postcommdistributionsByParent Error Response","schema":{"$ref":"#/definitions/postcommdistributionsByParentErrorResponse"}},"422":{"description":"postcommdistributionsByParent Error Response","schema":{"$ref":"#/definitions/postcommdistributionsByParentErrorResponse"}},"500":{"description":"postcommdistributionsByParent Error Response","schema":{"$ref":"#/definitions/postcommdistributionsByParentErrorResponse"}}}}},"/party/commdistributions":{"post":{"summary":"Creates Transfer agent distribution commission with parent mentioned in the payload","description":"Creates Transfer agent distribution commission with parent mentioned in the payload","operationId":"postcommdistributions","produces":["application/json"],"parameters":[{"name":"referenceId","in":"header","description":"uniqueId for security purpose","required":false,"type":"string"},{"name":"token","in":"header","description":"unique token","required":false,"type":"string"},{"name":"username","in":"header","description":"username","required":false,"type":"string"},{"name":"company","in":"header","description":"company name","required":false,"type":"string"},{"name":"command","in":"header","description":"API operations like INVOKE, VALIDATE, PROCESS can be set or by default PROCESS is set","required":false,"type":"string"},{"in":"body","name":"Payload","description":"postcommdistributions Payload","required":true,"schema":{"$ref":"#/definitions/sDistributionV1.0.0Payload"}}],"responses":{"201":{"description":"postcommdistributions Success Response","schema":{"$ref":"#/definitions/postcommdistributionsSuccessResponse"}},"400":{"description":"postcommdistributions Error Response","schema":{"$ref":"#/definitions/postcommdistributionsErrorResponse"}},"401":{"description":"postcommdistributions Error Response","schema":{"$ref":"#/definitions/postcommdistributionsErrorResponse"}},"403":{"description":"postcommdistributions Error Response","schema":{"$ref":"#/definitions/postcommdistributionsErrorResponse"}},"404":{"description":"postcommdistributions Error Response","schema":{"$ref":"#/definitions/postcommdistributionsErrorResponse"}},"405":{"description":"postcommdistributions Error Response","schema":{"$ref":"#/definitions/postcommdistributionsErrorResponse"}},"409":{"description":"postcommdistributions Error Response","schema":{"$ref":"#/definitions/postcommdistributionsErrorResponse"}},"422":{"description":"postcommdistributions Error Response","schema":{"$ref":"#/definitions/postcommdistributionsErrorResponse"}},"500":{"description":"postcommdistributions Error Response","schema":{"$ref":"#/definitions/postcommdistributionsErrorResponse"}}}},"put":{"summary":"Updates Transfer agent distribution commission records with identifiers provided in the payload","description":"Updates Transfer agent distribution commission records with identifiers provided in the payload","operationId":"putcommdistributions","produces":["application/json"],"parameters":[{"name":"referenceId","in":"header","description":"uniqueId for security purpose","required":false,"type":"string"},{"name":"token","in":"header","description":"unique token","required":false,"type":"string"},{"name":"username","in":"header","description":"username","required":false,"type":"string"},{"name":"company","in":"header","description":"company name","required":false,"type":"string"},{"name":"command","in":"header","description":"API operations like INVOKE, VALIDATE, PROCESS can be set or by default PROCESS is set","required":false,"type":"string"},{"in":"body","name":"Payload","description":"putcommdistributions Payload","required":true,"schema":{"$ref":"#/definitions/sDistributionV1.0.0BULKPayload"}}],"responses":{"201":{"description":"putcommdistributions Success Response","schema":{"$ref":"#/definitions/putcommdistributionsSuccessResponse"}},"403":{"description":"putcommdistributions Error Response","schema":{"$ref":"#/definitions/putcommdistributionsErrorResponse"}},"404":{"description":"putcommdistributions Error Response","schema":{"$ref":"#/definitions/putcommdistributionsErrorResponse"}},"405":{"description":"putcommdistributions Error Response","schema":{"$ref":"#/definitions/putcommdistributionsErrorResponse"}},"409":{"description":"putcommdistributions Error Response","schema":{"$ref":"#/definitions/putcommdistributionsErrorResponse"}},"422":{"description":"putcommdistributions Error Response","schema":{"$ref":"#/definitions/putcommdistributionsErrorResponse"}},"500":{"description":"putcommdistributions Error Response","schema":{"$ref":"#/definitions/putcommdistributionsErrorResponse"}},"501":{"description":"putcommdistributions Error Response","schema":{"$ref":"#/definitions/putcommdistributionsErrorResponse"}}}},"delete":{"summary":"Deletes Transfer agent distribution commission records with identifiers provided in the payload","description":"Deletes Transfer agent distribution commission records with identifiers provided in the payload","operationId":"deletecommdistributions","produces":["application/json"],"parameters":[{"name":"referenceId","in":"header","description":"uniqueId for security purpose","required":false,"type":"string"},{"name":"token","in":"header","description":"unique token","required":false,"type":"string"},{"name":"username","in":"header","description":"username","required":false,"type":"string"},{"name":"company","in":"header","description":"company name","required":false,"type":"string"},{"name":"command","in":"header","description":"API operations like INVOKE, VALIDATE, PROCESS can be set or by default PROCESS is set","required":false,"type":"string"},{"in":"body","name":"Payload","description":"deletecommdistributions Payload","required":true,"schema":{"$ref":"#/definitions/sDistributionV1.0.0BULKPayload"}}],"responses":{"200":{"description":"deletecommdistributions Success Response","schema":{"$ref":"#/definitions/deletecommdistributionsSuccessResponse"}},"403":{"description":"deletecommdistributions Error Response","schema":{"$ref":"#/definitions/deletecommdistributionsErrorResponse"}},"404":{"description":"deletecommdistributions Error Response","schema":{"$ref":"#/definitions/deletecommdistributionsErrorResponse"}},"405":{"description":"deletecommdistributions Error Response","schema":{"$ref":"#/definitions/deletecommdistributionsErrorResponse"}},"422":{"description":"deletecommdistributions Error Response","schema":{"$ref":"#/definitions/deletecommdistributionsErrorResponse"}}}}},"/party/commdistributions/{internalId}":{"get":{"summary":"Retrieves a specific Transfer agent distribution commission record","description":"Retrieves a specific Transfer agent distribution commission record","operationId":"getcommdistributionsByInternalId","produces":["application/json"],"parameters":[{"name":"page","in":"query","description":"Current page number (Default:1)","required":false,"type":"number"},{"name":"size","in":"query","description":"Total number of records per page (Default:25)","required":false,"type":"number"},{"name":"orders","in":"query","description":"An 'orders' parameter allows you to specify the order in which rows appear in the result set Eg: orders=fundname:0,masterfund:1 where 'fundname' is field, '0' for ascending manner and ',' as seperator for fields","required":false,"type":"string"},{"name":"groups","in":"query","description":"A 'groups' parameter is used to collect data across multiple records and group the results by one or more columns. Eg: groups=nationality,reclaimtax-nationality:EQ:Indian,reclaimtax:EQ:N-nationality:COUNT where 'nationality,reclaimtax' is for the fields and 'nationality:EQ:Indian,reclaimtax:EQ:N-nationality' are filters, 'nationality:COUNT' is a aggregator and '-' as seperator ","required":false,"type":"string"},{"name":"filters","in":"query","description":"Use a 'filters' parameter to select rows based on a value by using basic operators like EQ, NE etc.., Eg: filters=statistictype:NE:SRS where 'statistictype' is a field, 'NE' is a operator and 'SRS' is a value","required":false,"type":"string"},{"name":"referenceId","in":"header","description":"uniqueId for security purpose","required":false,"type":"string"},{"name":"token","in":"header","description":"unique token","required":false,"type":"string"},{"name":"username","in":"header","description":"username","required":false,"type":"string"},{"name":"company","in":"header","description":"company name","required":false,"type":"string"},{"name":"command","in":"header","description":"API operations like INVOKE, VALIDATE, PROCESS can be set or by default PROCESS is set","required":false,"type":"string"},{"name":"internalId","in":"path","description":"internalId","required":true,"type":"string"}],"responses":{"200":{"description":"getcommdistributionsByInternalId Success Response","schema":{"$ref":"#/definitions/getcommdistributionsByInternalIdSuccessResponse"}},"400":{"description":"getcommdistributionsByInternalId Error Response","schema":{"$ref":"#/definitions/getcommdistributionsByInternalIdErrorResponse"}},"403":{"description":"getcommdistributionsByInternalId Error Response","schema":{"$ref":"#/definitions/getcommdistributionsByInternalIdErrorResponse"}},"404":{"description":"getcommdistributionsByInternalId Error Response","schema":{"$ref":"#/definitions/getcommdistributionsByInternalIdErrorResponse"}},"422":{"description":"getcommdistributionsByInternalId Error Response","schema":{"$ref":"#/definitions/getcommdistributionsByInternalIdErrorResponse"}},"500":{"description":"getcommdistributionsByInternalId Error Response","schema":{"$ref":"#/definitions/getcommdistributionsByInternalIdErrorResponse"}},"501":{"description":"getcommdistributionsByInternalId Error Response","schema":{"$ref":"#/definitions/getcommdistributionsByInternalIdErrorResponse"}}}},"put":{"summary":"Updates a specific Transfer agent distribution commission record","description":"Updates a specific Transfer agent distribution commission record","operationId":"putcommdistributionsById","produces":["application/json"],"parameters":[{"name":"referenceId","in":"header","description":"uniqueId for security purpose","required":false,"type":"string"},{"name":"token","in":"header","description":"unique token","required":false,"type":"string"},{"name":"username","in":"header","description":"username","required":false,"type":"string"},{"name":"company","in":"header","description":"company name","required":false,"type":"string"},{"name":"command","in":"header","description":"API operations like INVOKE, VALIDATE, PROCESS can be set or by default PROCESS is set","required":false,"type":"string"},{"name":"internalId","in":"path","description":"internalId","required":true,"type":"string"},{"in":"body","name":"Payload","description":"putcommdistributionsById Payload","required":true,"schema":{"$ref":"#/definitions/sDistributionV1.0.0Payload"}}],"responses":{"201":{"description":"putcommdistributionsById Success Response","schema":{"$ref":"#/definitions/putcommdistributionsByIdSuccessResponse"}},"403":{"description":"putcommdistributionsById Error Response","schema":{"$ref":"#/definitions/putcommdistributionsByIdErrorResponse"}},"404":{"description":"putcommdistributionsById Error Response","schema":{"$ref":"#/definitions/putcommdistributionsByIdErrorResponse"}},"405":{"description":"putcommdistributionsById Error Response","schema":{"$ref":"#/definitions/putcommdistributionsByIdErrorResponse"}},"409":{"description":"putcommdistributionsById Error Response","schema":{"$ref":"#/definitions/putcommdistributionsByIdErrorResponse"}},"422":{"description":"putcommdistributionsById Error Response","schema":{"$ref":"#/definitions/putcommdistributionsByIdErrorResponse"}},"500":{"description":"putcommdistributionsById Error Response","schema":{"$ref":"#/definitions/putcommdistributionsByIdErrorResponse"}},"501":{"description":"putcommdistributionsById Error Response","schema":{"$ref":"#/definitions/putcommdistributionsByIdErrorResponse"}}}},"delete":{"summary":"Updates a specific Transfer agent distribution commission record for the specified parent","description":"Updates a specific Transfer agent distribution commission record for the specified parent","operationId":"deletecommdistributionsById","produces":["application/json"],"parameters":[{"name":"referenceId","in":"header","description":"uniqueId for security purpose","required":false,"type":"string"},{"name":"token","in":"header","description":"unique token","required":false,"type":"string"},{"name":"username","in":"header","description":"username","required":false,"type":"string"},{"name":"company","in":"header","description":"company name","required":false,"type":"string"},{"name":"command","in":"header","description":"API operations like INVOKE, VALIDATE, PROCESS can be set or by default PROCESS is set","required":false,"type":"string"},{"name":"internalId","in":"path","description":"internalId","required":true,"type":"string"},{"in":"body","name":"Payload","description":"deletecommdistributionsById Payload","required":false,"schema":{"$ref":"#/definitions/sDistributionV1.0.0Payload"}}],"responses":{"200":{"description":"deletecommdistributionsById Success Response","schema":{"$ref":"#/definitions/deletecommdistributionsByIdSuccessResponse"}},"403":{"description":"deletecommdistributionsById Error Response","schema":{"$ref":"#/definitions/deletecommdistributionsByIdErrorResponse"}},"404":{"description":"deletecommdistributionsById Error Response","schema":{"$ref":"#/definitions/deletecommdistributionsByIdErrorResponse"}},"405":{"description":"deletecommdistributionsById Error Response","schema":{"$ref":"#/definitions/deletecommdistributionsByIdErrorResponse"}},"422":{"description":"deletecommdistributionsById Error Response","schema":{"$ref":"#/definitions/deletecommdistributionsByIdErrorResponse"}}}}}},"definitions":{"sDistributionV1.0.0Payload":{"properties":{"header":{"type":"object"},"body":{"$ref":"#/definitions/sDistributionV1.0.0"}}},"paginationSchema":{"properties":{"page":{"type":"string"},"size":{"type":"string"},"count":{"type":"string"},"total":{"type":"string"}}},"auditSchema":{"properties":{"startTime":{"type":"string"},"endTime":{"type":"string"},"processTime":{"type":"string"}}},"successHeaderstatusSchema":{"properties":{"result":{"type":"string"},"HTTP_MESSAGE":{"type":"string"},"description":{"type":"string"},"message":{"type":"string"},"HTTP_CODE":{"type":"string"},"requestId":{"type":"string"},"responseId":{"type":"string"},"eTag":{"type":"string"},"lastModified":{"type":"string"}}},"postcommdistributionsByParentSuccessheaderResponse":{"properties":{"pagination":{"$ref":"#/definitions/paginationSchema"},"audit":{"$ref":"#/definitions/auditSchema"},"status":{"$ref":"#/definitions/successHeaderstatusSchema"},"company":{"type":"string"},"username":{"type":"string"},"referenceId":{"type":"string"},"token":{"type":"string"}}},"postcommdistributionsByParentrecordsSchema":{"type":"array","items":{"$ref":"#/definitions/sDistributionV1.0.0"}},"postcommdistributionsByParentSuccessbodyResponse":{"properties":{"records":{"$ref":"#/definitions/postcommdistributionsByParentrecordsSchema"}}},"postcommdistributionsByParentSuccessResponse":{"properties":{"header":{"$ref":"#/definitions/postcommdistributionsByParentSuccessheaderResponse"},"body":{"$ref":"#/definitions/postcommdistributionsByParentSuccessbodyResponse"}}},"errorHeaderstatusSchema":{"properties":{"result":{"type":"string"},"HTTP_MESSAGE":{"type":"string"},"description":{"type":"string"},"message":{"type":"string"},"HTTP_CODE":{"type":"string"},"requestId":{"type":"string"},"responseId":{"type":"string"},"eTag":{"type":"string"},"lastModified":{"type":"string"},"details":{"type":"array","items":{"type":"object","properties":{"code":{"type":"string"},"message":{"type":"string"},"type":{"type":"string"}}}}}},"postcommdistributionsByParentErrorheaderResponse":{"properties":{"pagination":{"$ref":"#/definitions/paginationSchema"},"audit":{"$ref":"#/definitions/auditSchema"},"status":{"$ref":"#/definitions/errorHeaderstatusSchema"},"referenceId":{"type":"string"},"token":{"type":"string"},"username":{"type":"string"}}},"postcommdistributionsByParentErrorbodyResponse":{"properties":{"items":{"type":"array","items":{"type":"object","properties":{"code":{"type":"string"},"message":{"type":"string"},"type":{"type":"string"}}}}}},"postcommdistributionsByParentErrorResponse":{"properties":{"header":{"$ref":"#/definitions/postcommdistributionsByParentErrorheaderResponse"},"body":{"type":"object"}}},"sDistributionV1.0.0":{"properties":{"reference":{"type":"string","description":"Contains external and internal identifiers of the record"},"entityType":{"type":"string","description":"Identifies the entity. For e.g. 0001 for registers, 0002 for agents, 0007 for investors, etc."},"internalId":{"type":"string","description":"Internal identifier of the records.  Generated by the system during POST and can be used for other operations"},"extIdType":{"type":"string","description":"Provider of the external identification"},"externalId":{"type":"string","description":"External identifier of the record"},"promoterInternalId":{"type":"string","description":"Internal identifier of the Fund promoter linked to the entity"},"promoterExternalId":{"type":"string","description":"External identifier of the Fund promoter linked to the entity"},"parent":{"type":"string","description":"Contains external and internal identifiers of the parent record, if the current record belongs to sub entities"},"parentEntityType":{"type":"string","description":"Identifies the parent entity. For e.g. 0001 for registers, 0002 for agents, 0007 for investors, etc."},"parentInternalId":{"type":"string","description":"Internal identifier of the parent record"},"parentExternalId":{"type":"string","description":"External identifier of the parent record"},"parentPromoterInternalId":{"type":"string","description":"Internal identifier of the Fund promoter linked to the parent entity"},"parentPromoterExternalId":{"type":"string","description":"External identifier of the Fund promoter linked to the parent entity"},"distribution":{"type":"string","description":"Contains individual attributes of the Distribution entity"},"agentDistributionId":{"type":"number","description":"Internal ID of the  Agent  who will get the commission. Allowed values are from the list of Ids defined in MFGI."},"agentDistributionExternalId":{"type":"string","description":"External ID of the  Agent who will get the commission."},"agentPaymentId":{"type":"number","description":"Internal ID of the  Agent to which the TA has to pay the defined commission."},"agentPaymentExternalId":{"type":"string","description":"External ID of the  Agent to which the TA has to pay the defined commission."},"shareClassCode":{"type":"string","description":"The share class code linked to the fund for commission distribution. Allowed values are from the list of Ids defined in MFGI."},"taFundId":{"type":"string","description":"Internal ID of the TA Fund distributed by the agent."},"taFundExternalId":{"type":"string","description":"External ID of the TA Fund distributed by the agent."},"operationCode":{"type":"string","description":"Operation code for agent commission distribution definition. For example: 0001(Subscription), 0002(Redemption), 0006(Transfer), 0007(Switch)etc. The LoV is available in the CMESS table TA_COPER."},"percentage":{"type":"number","description":"The percentage of the commission distribution."},"specificInitialChargePercentage":{"type":"number","description":"The specific initial charge percentage."},"niveau":{"type":"number","description":"niveau"},"agentCommissionType":{"type":"string","description":"It specifies the commission type of the agent. For example: 0001(FEL), 0002(Pre- finance fee), 0003(Purchase fee)etc. The LoV is available in the CMESS table COMM_TYPE."}}},"postcommdistributionsSuccessheaderResponse":{"properties":{"pagination":{"$ref":"#/definitions/paginationSchema"},"audit":{"$ref":"#/definitions/auditSchema"},"status":{"$ref":"#/definitions/successHeaderstatusSchema"},"company":{"type":"string"},"username":{"type":"string"},"referenceId":{"type":"string"},"token":{"type":"string"}}},"postcommdistributionsrecordsSchema":{"type":"array","items":{"$ref":"#/definitions/sDistributionV1.0.0"}},"postcommdistributionsSuccessbodyResponse":{"properties":{"records":{"$ref":"#/definitions/postcommdistributionsrecordsSchema"}}},"postcommdistributionsSuccessResponse":{"properties":{"header":{"$ref":"#/definitions/postcommdistributionsSuccessheaderResponse"},"body":{"$ref":"#/definitions/postcommdistributionsSuccessbodyResponse"}}},"postcommdistributionsErrorheaderResponse":{"properties":{"pagination":{"$ref":"#/definitions/paginationSchema"},"audit":{"$ref":"#/definitions/auditSchema"},"status":{"$ref":"#/definitions/errorHeaderstatusSchema"},"referenceId":{"type":"string"},"token":{"type":"string"},"username":{"type":"string"}}},"postcommdistributionsErrorbodyResponse":{"properties":{"items":{"type":"array","items":{"type":"object","properties":{"code":{"type":"string"},"message":{"type":"string"},"type":{"type":"string"}}}}}},"postcommdistributionsErrorResponse":{"properties":{"header":{"$ref":"#/definitions/postcommdistributionsErrorheaderResponse"},"body":{"type":"object"}}},"getcommdistributionsByInternalIdSuccessheaderResponse":{"properties":{"pagination":{"$ref":"#/definitions/paginationSchema"},"audit":{"$ref":"#/definitions/auditSchema"},"status":{"$ref":"#/definitions/successHeaderstatusSchema"},"company":{"type":"string"},"username":{"type":"string"},"referenceId":{"type":"string"},"token":{"type":"string"}}},"getcommdistributionsByInternalIdrecordsSchema":{"type":"array","items":{"$ref":"#/definitions/sDistributionV1.0.0"}},"getcommdistributionsByInternalIdSuccessbodyResponse":{"properties":{"records":{"$ref":"#/definitions/getcommdistributionsByInternalIdrecordsSchema"}}},"getcommdistributionsByInternalIdSuccessResponse":{"properties":{"header":{"$ref":"#/definitions/getcommdistributionsByInternalIdSuccessheaderResponse"},"body":{"$ref":"#/definitions/getcommdistributionsByInternalIdSuccessbodyResponse"}}},"getcommdistributionsByInternalIdErrorheaderResponse":{"properties":{"pagination":{"$ref":"#/definitions/paginationSchema"},"audit":{"$ref":"#/definitions/auditSchema"},"status":{"$ref":"#/definitions/errorHeaderstatusSchema"},"referenceId":{"type":"string"},"token":{"type":"string"},"username":{"type":"string"}}},"getcommdistributionsByInternalIdErrorbodyResponse":{"properties":{"items":{"type":"array","items":{"type":"object","properties":{"code":{"type":"string"},"message":{"type":"string"},"type":{"type":"string"}}}}}},"getcommdistributionsByInternalIdErrorResponse":{"properties":{"header":{"$ref":"#/definitions/getcommdistributionsByInternalIdErrorheaderResponse"},"body":{"type":"object"}}},"putcommdistributionsByIdSuccessheaderResponse":{"properties":{"pagination":{"$ref":"#/definitions/paginationSchema"},"audit":{"$ref":"#/definitions/auditSchema"},"status":{"$ref":"#/definitions/successHeaderstatusSchema"},"company":{"type":"string"},"username":{"type":"string"},"referenceId":{"type":"string"},"token":{"type":"string"}}},"putcommdistributionsByIdrecordsSchema":{"type":"array","items":{"$ref":"#/definitions/sDistributionV1.0.0"}},"putcommdistributionsByIdSuccessbodyResponse":{"properties":{"records":{"$ref":"#/definitions/putcommdistributionsByIdrecordsSchema"}}},"putcommdistributionsByIdSuccessResponse":{"properties":{"header":{"$ref":"#/definitions/putcommdistributionsByIdSuccessheaderResponse"},"body":{"$ref":"#/definitions/putcommdistributionsByIdSuccessbodyResponse"}}},"putcommdistributionsByIdErrorheaderResponse":{"properties":{"pagination":{"$ref":"#/definitions/paginationSchema"},"audit":{"$ref":"#/definitions/auditSchema"},"status":{"$ref":"#/definitions/errorHeaderstatusSchema"},"referenceId":{"type":"string"},"token":{"type":"string"},"username":{"type":"string"}}},"putcommdistributionsByIdErrorbodyResponse":{"properties":{"items":{"type":"array","items":{"type":"object","properties":{"code":{"type":"string"},"message":{"type":"string"},"type":{"type":"string"}}}}}},"putcommdistributionsByIdErrorResponse":{"properties":{"header":{"$ref":"#/definitions/putcommdistributionsByIdErrorheaderResponse"},"body":{"type":"object"}}},"sDistributionV1.0.0BULKPayload":{"properties":{"header":{"type":"object"},"body":{"type":"object","properties":{"distributions":{"type":"array","items":{"$ref":"#/definitions/sDistributionV1.0.0"}}}}}},"putcommdistributionsSuccessheaderResponse":{"properties":{"pagination":{"$ref":"#/definitions/paginationSchema"},"audit":{"$ref":"#/definitions/auditSchema"},"status":{"$ref":"#/definitions/successHeaderstatusSchema"},"company":{"type":"string"},"username":{"type":"string"},"referenceId":{"type":"string"},"token":{"type":"string"}}},"putcommdistributionsrecordsSchema":{"type":"array","items":{"$ref":"#/definitions/sDistributionV1.0.0"}},"putcommdistributionsSuccessbodyResponse":{"properties":{"records":{"$ref":"#/definitions/putcommdistributionsrecordsSchema"}}},"putcommdistributionsSuccessResponse":{"properties":{"header":{"$ref":"#/definitions/putcommdistributionsSuccessheaderResponse"},"body":{"$ref":"#/definitions/putcommdistributionsSuccessbodyResponse"}}},"putcommdistributionsErrorheaderResponse":{"properties":{"pagination":{"$ref":"#/definitions/paginationSchema"},"audit":{"$ref":"#/definitions/auditSchema"},"status":{"$ref":"#/definitions/errorHeaderstatusSchema"},"referenceId":{"type":"string"},"token":{"type":"string"},"username":{"type":"string"}}},"putcommdistributionsErrorbodyResponse":{"properties":{"items":{"type":"array","items":{"type":"object","properties":{"code":{"type":"string"},"message":{"type":"string"},"type":{"type":"string"}}}}}},"putcommdistributionsErrorResponse":{"properties":{"header":{"$ref":"#/definitions/putcommdistributionsErrorheaderResponse"},"body":{"type":"object"}}},"deletecommdistributionsSuccessheaderResponse":{"properties":{"pagination":{"$ref":"#/definitions/paginationSchema"},"audit":{"$ref":"#/definitions/auditSchema"},"status":{"$ref":"#/definitions/successHeaderstatusSchema"},"company":{"type":"string"},"username":{"type":"string"},"referenceId":{"type":"string"},"token":{"type":"string"}}},"deletecommdistributionsrecordsSchema":{"type":"array","items":{"$ref":"#/definitions/sDistributionV1.0.0"}},"deletecommdistributionsSuccessbodyResponse":{"properties":{"records":{"$ref":"#/definitions/deletecommdistributionsrecordsSchema"}}},"deletecommdistributionsSuccessResponse":{"properties":{"header":{"$ref":"#/definitions/deletecommdistributionsSuccessheaderResponse"},"body":{"$ref":"#/definitions/deletecommdistributionsSuccessbodyResponse"}}},"deletecommdistributionsErrorheaderResponse":{"properties":{"pagination":{"$ref":"#/definitions/paginationSchema"},"audit":{"$ref":"#/definitions/auditSchema"},"status":{"$ref":"#/definitions/errorHeaderstatusSchema"},"referenceId":{"type":"string"},"token":{"type":"string"},"username":{"type":"string"}}},"deletecommdistributionsErrorbodyResponse":{"properties":{"items":{"type":"array","items":{"type":"object","properties":{"code":{"type":"string"},"message":{"type":"string"},"type":{"type":"string"}}}}}},"deletecommdistributionsErrorResponse":{"properties":{"header":{"$ref":"#/definitions/deletecommdistributionsErrorheaderResponse"},"body":{"type":"object"}}},"deletecommdistributionsByIdSuccessheaderResponse":{"properties":{"pagination":{"$ref":"#/definitions/paginationSchema"},"audit":{"$ref":"#/definitions/auditSchema"},"status":{"$ref":"#/definitions/successHeaderstatusSchema"},"company":{"type":"string"},"username":{"type":"string"},"referenceId":{"type":"string"},"token":{"type":"string"}}},"deletecommdistributionsByIdrecordsSchema":{"type":"array","items":{"$ref":"#/definitions/sDistributionV1.0.0"}},"deletecommdistributionsByIdSuccessbodyResponse":{"properties":{"records":{"$ref":"#/definitions/deletecommdistributionsByIdrecordsSchema"}}},"deletecommdistributionsByIdSuccessResponse":{"properties":{"header":{"$ref":"#/definitions/deletecommdistributionsByIdSuccessheaderResponse"},"body":{"$ref":"#/definitions/deletecommdistributionsByIdSuccessbodyResponse"}}},"deletecommdistributionsByIdErrorheaderResponse":{"properties":{"pagination":{"$ref":"#/definitions/paginationSchema"},"audit":{"$ref":"#/definitions/auditSchema"},"status":{"$ref":"#/definitions/errorHeaderstatusSchema"},"referenceId":{"type":"string"},"token":{"type":"string"},"username":{"type":"string"}}},"deletecommdistributionsByIdErrorbodyResponse":{"properties":{"items":{"type":"array","items":{"type":"object","properties":{"code":{"type":"string"},"message":{"type":"string"},"type":{"type":"string"}}}}}},"deletecommdistributionsByIdErrorResponse":{"properties":{"header":{"$ref":"#/definitions/deletecommdistributionsByIdErrorheaderResponse"},"body":{"type":"object"}}}}}